abagen/__init__.py
abagen/_version.py
abagen/allen.py
abagen/correct.py
abagen/images.py
abagen/info.py
abagen/io.py
abagen/matching.py
abagen/probes_.py
abagen/reporting.py
abagen/samples_.py
abagen/surfaces.py
abagen/transforms.py
abagen/utils.py
abagen/cli/__init__.py
abagen/cli/run.py
abagen/data/atlas-desikankilliany-lh.label.gii.gz
abagen/data/atlas-desikankilliany-rh.label.gii.gz
abagen/data/atlas-desikankilliany.csv
abagen/data/atlas-desikankilliany.nii.gz
abagen/data/burt2018_natneuro.csv.gz
abagen/data/corrected_mni_coordinates.csv.gz
abagen/data/donor_info.csv
abagen/data/fsaverage5-pial-lh.surf.gii.gz
abagen/data/fsaverage5-pial-rh.surf.gii.gz
abagen/data/reannotated.csv.gz
abagen/data/rubinov2015_pnas.csv.gz
abagen/data/native_dk/10021/atlas-desikankilliany-lh.label.gii.gz
abagen/data/native_dk/10021/atlas-desikankilliany-rh.label.gii.gz
abagen/data/native_dk/10021/atlas-desikankilliany.nii.gz
abagen/data/native_dk/12876/atlas-desikankilliany-lh.label.gii.gz
abagen/data/native_dk/12876/atlas-desikankilliany-rh.label.gii.gz
abagen/data/native_dk/12876/atlas-desikankilliany.nii.gz
abagen/data/native_dk/14380/atlas-desikankilliany-lh.label.gii.gz
abagen/data/native_dk/14380/atlas-desikankilliany-rh.label.gii.gz
abagen/data/native_dk/14380/atlas-desikankilliany.nii.gz
abagen/data/native_dk/15496/atlas-desikankilliany-lh.label.gii.gz
abagen/data/native_dk/15496/atlas-desikankilliany-rh.label.gii.gz
abagen/data/native_dk/15496/atlas-desikankilliany.nii.gz
abagen/data/native_dk/15697/atlas-desikankilliany-lh.label.gii.gz
abagen/data/native_dk/15697/atlas-desikankilliany-rh.label.gii.gz
abagen/data/native_dk/15697/atlas-desikankilliany.nii.gz
abagen/data/native_dk/9861/atlas-desikankilliany-lh.label.gii.gz
abagen/data/native_dk/9861/atlas-desikankilliany-rh.label.gii.gz
abagen/data/native_dk/9861/atlas-desikankilliany.nii.gz
abagen/datasets/__init__.py
abagen/datasets/fetchers.py
abagen/datasets/utils.py
abagen/mouse/__init__.py
abagen/mouse/gene.py
abagen-0.1.3.dist-info/LICENSE
abagen-0.1.3.dist-info/METADATA
abagen-0.1.3.dist-info/WHEEL
abagen-0.1.3.dist-info/entry_points.txt
abagen-0.1.3.dist-info/top_level.txt
abagen-0.1.3.dist-info/RECORD
