Metadata-Version: 2.1
Name: abagen
Version: 0.1.3
Summary: A toolbox for working with the Allen Brain Atlas genetic data
Home-page: https://github.com/rmarkello/abagen
Author: abagen developers
Maintainer: Ross Markello
Maintainer-email: rossmarkello@gmail.com
License: BSD-3
Download-URL: https://github.com/rmarkello/abagen
Platform: OS Independent
Classifier: Development Status :: 3 - Alpha
Classifier: Intended Audience :: Science/Research
Classifier: License :: OSI Approved :: BSD License
Classifier: Operating System :: OS Independent
Classifier: Programming Language :: Python
Classifier: Programming Language :: Python :: 3.6
Classifier: Programming Language :: Python :: 3.7
Classifier: Topic :: Scientific/Engineering
Provides: abagen
Requires-Python: >=3.6
Requires-Dist: nibabel
Requires-Dist: numpy (>=1.14)
Requires-Dist: pandas (>=0.25.0)
Requires-Dist: scipy
Provides-Extra: all
Requires-Dist: sphinx (>=2.0) ; extra == 'all'
Requires-Dist: sphinx-argparse ; extra == 'all'
Requires-Dist: sphinx-rtd-theme ; extra == 'all'
Requires-Dist: fastparquet ; extra == 'all'
Requires-Dist: python-snappy ; extra == 'all'
Requires-Dist: coverage ; extra == 'all'
Requires-Dist: pytest (>=3.6) ; extra == 'all'
Requires-Dist: pytest-cov ; extra == 'all'
Provides-Extra: doc
Requires-Dist: sphinx (>=2.0) ; extra == 'doc'
Requires-Dist: sphinx-argparse ; extra == 'doc'
Requires-Dist: sphinx-rtd-theme ; extra == 'doc'
Provides-Extra: io
Requires-Dist: fastparquet ; extra == 'io'
Requires-Dist: python-snappy ; extra == 'io'
Provides-Extra: style
Requires-Dist: flake8 ; extra == 'style'
Provides-Extra: test
Requires-Dist: coverage ; extra == 'test'
Requires-Dist: pytest (>=3.6) ; extra == 'test'
Requires-Dist: pytest-cov ; extra == 'test'
